lab_mic/__init__.py
lab_mic/recorder.py
lab_mic-0.2.0.dist-info/METADATA
lab_mic-0.2.0.dist-info/WHEEL
lab_mic-0.2.0.dist-info/top_level.txt
lab_mic-0.2.0.dist-info/RECORD
