Metadata-Version: 2.4
Name: lab_mic
Version: 0.2.0
Summary: Record audio directly within Jupyter/IPython/Colab using the browser microphone and ffmpeg.
Author-email: voidful <voidful.stack@gmail.com>
License: MIT
Classifier: Programming Language :: Python :: 3
Classifier: License :: OSI Approved :: MIT License
Classifier: Operating System :: OS Independent
Classifier: Framework :: IPython
Classifier: Framework :: Jupyter
Classifier: Topic :: Multimedia :: Sound/Audio :: Capture/Recording
Classifier: Intended Audience :: Developers
Classifier: Intended Audience :: Science/Research
Requires-Python: >=3.8
Requires-Dist: numpy
Requires-Dist: scipy
Requires-Dist: ffmpeg-python
Requires-Dist: ipython
Requires-Dist: ipywidgets>=7.0.0
